group2p/__init__.py
group2p/group2p.py
group2p/groupme.py
group2p-0.4.0.dist-info/LICENSE
group2p-0.4.0.dist-info/METADATA
group2p-0.4.0.dist-info/WHEEL
group2p-0.4.0.dist-info/top_level.txt
group2p-0.4.0.dist-info/RECORD
