Metadata-Version: 2.1
Name: group2p
Version: 0.4.0
Summary: A wrapper for communicating between clients via GroupMe.
License: MIT
Requires: requests
License-File: LICENSE
